screen_ws2812b/src/screen_fsm/screen_fsm.v
module screen_fsm #(
    parameter LED_COUNT  = 256,
    parameter BITS_COUNT = 24
)(
    input  sys_clk,
    input  rst_n,
    input  in_init,
    output wire [7:0] out_fb_read_addr,
    output reg       out_fb_read_enable,
    
    output reg       out_shift_load,
    output reg       out_shift_shift,
    
    output reg       out_pulse_start,
    output reg       out_pulse_send_reset,
    
    input  in_pulse_high_done,
    input  in_pulse_reset_done,
    input  in_pulse_done
);

localparam START         = 5'd0;
localparam READ_PIXEL    = 5'd1;
localparam LOAD_SHIFT    = 5'd2;
localparam RUN_SCREEN    = 5'd3;
localparam WAIT_HIGH     = 5'd4;
localparam SHIFT_NEXT    = 5'd5;
localparam CHECK_BITS    = 5'd6;
localparam NEXT_PIXEL    = 5'd7;
localparam SEND_RESET    = 5'd8;
localparam WAIT_RESET    = 5'd9;
localparam WAIT_PULSE    = 5'd10;

localparam RST_VALUE_PC = 
    `ifdef BENCH
        8'd0
    `else
        8'd0
    `endif; 

reg [4:0] state;
reg [7:0] pixel_counter;
reg [4:0] bit_counter;
assign out_fb_read_addr = pixel_counter;

always @(posedge sys_clk ) begin
    if (!rst_n) begin
        bit_counter <= 8'b0;
        pixel_counter <= RST_VALUE_PC;
        state <= START;
    end else begin
        case (state)
            START : begin
                bit_counter <= 8'b0;
                pixel_counter <= RST_VALUE_PC;
                state <= in_init ? READ_PIXEL : START;
            end 
            READ_PIXEL : state <= LOAD_SHIFT;
            LOAD_SHIFT : state <= RUN_SCREEN;
            RUN_SCREEN : state <= WAIT_HIGH;
            WAIT_HIGH : state <= in_pulse_high_done ? SHIFT_NEXT : WAIT_HIGH;
            SHIFT_NEXT : begin
                state <= CHECK_BITS;
                bit_counter <= bit_counter + 1;
            end
            CHECK_BITS : begin
                if (bit_counter == BITS_COUNT -1) begin
                    pixel_counter <= pixel_counter + 1;
                    state <= NEXT_PIXEL;
                end else state <= WAIT_HIGH;
            end
            NEXT_PIXEL : begin
                if (pixel_counter == LED_COUNT - 1) begin
                    state <= WAIT_PULSE;
                end else begin
                    bit_counter <= 8'b0;
                    state <= READ_PIXEL;
                end
            end
            WAIT_PULSE : state <= in_pulse_done ? SEND_RESET : WAIT_PULSE;
            SEND_RESET : state <= WAIT_RESET;
            WAIT_RESET : state <= in_pulse_reset_done ? START : WAIT_RESET;
            default: state <= START;
        endcase
    end
end



always @(*) begin
    case (state)
    START:begin
        out_fb_read_enable = 1'b0;
        out_shift_load = 1'b0;
        out_shift_shift = 1'b0;
        out_pulse_start = 1'b0;
        out_pulse_send_reset = 1'b0;
    end
    READ_PIXEL : begin
        out_fb_read_enable = 1'b1;
        out_shift_load = 1'b0;
        out_shift_shift = 1'b0;
        out_pulse_start = 1'b0;
        out_pulse_send_reset = 1'b0;
    end
    LOAD_SHIFT : begin
        out_fb_read_enable = 1'b0;
        out_shift_load = 1'b1;
        out_shift_shift = 1'b0;
        out_pulse_start = 1'b0;
        out_pulse_send_reset = 1'b0;
    end
    RUN_SCREEN : begin
        out_fb_read_enable = 1'b0;
        out_shift_load = 1'b0;
        out_shift_shift = 1'b0;
        out_pulse_start = 1'b1;
        out_pulse_send_reset = 1'b0;
    end
    WAIT_HIGH : begin
        out_fb_read_enable = 1'b0;
        out_shift_load = 1'b0;
        out_shift_shift = 1'b0;
        out_pulse_start = 1'b1;
        out_pulse_send_reset = 1'b0;
    end
    SHIFT_NEXT : begin
        out_fb_read_enable = 1'b0;
        out_shift_load = 1'b0;
        out_shift_shift = 1'b1;
        out_pulse_start = 1'b1;
        out_pulse_send_reset = 1'b0;
    end
    CHECK_BITS : begin
        out_fb_read_enable = 1'b0;
        out_shift_load = 1'b0;
        out_shift_shift = 1'b0;
        out_pulse_start = 1'b1;
        out_pulse_send_reset = 1'b0;
    end
    NEXT_PIXEL : begin
        out_fb_read_enable = 1'b0;
        out_shift_load = 1'b0;
        out_shift_shift = 1'b0;
        out_pulse_start = 1'b0;
        out_pulse_send_reset = 1'b0;
    end
    WAIT_PULSE : begin
        out_fb_read_enable = 1'b0;
        out_shift_load = 1'b0;
        out_shift_shift = 1'b0;
        out_pulse_start = 1'b0;
        out_pulse_send_reset = 1'b0;
    end
    SEND_RESET : begin
        out_fb_read_enable = 1'b0;
        out_shift_load = 1'b0;
        out_shift_shift = 1'b0;
        out_pulse_start = 1'b0;
        out_pulse_send_reset = 1'b1;
    end
    WAIT_RESET : begin
        out_fb_read_enable = 1'b0;
        out_shift_load = 1'b0;
        out_shift_shift = 1'b0;
        out_pulse_start = 1'b0;
        out_pulse_send_reset = 1'b0;
    end
    default: begin
        out_fb_read_enable = 1'b0;
        out_shift_load = 1'b0;
        out_shift_shift = 1'b0;
        out_pulse_start = 1'b0;
        out_pulse_send_reset = 1'b0;
    end
endcase
end

`ifdef BENCH
    reg [8*40:1] state_name;
    always @(*) begin
        case (state)
            START:        state_name = "START";
            READ_PIXEL: state_name = "READ_PIXEL";
            LOAD_SHIFT: state_name = "LOAD_SHIFT";
            RUN_SCREEN: state_name = "RUN_SCREEN";
            WAIT_HIGH:        state_name = "WAIT_HIGH";
            SHIFT_NEXT:   state_name = "SHIFT_NEXT";
            CHECK_BITS:       state_name = "CHECK_BITS";
            NEXT_PIXEL:         state_name = "NEXT_PIXEL";
            WAIT_PULSE:    state_name = "WAIT_PULSE";
            SEND_RESET:   state_name = "SEND_RESET";
            WAIT_RESET:   state_name = "WAIT_RESET";
        endcase
    end
`endif

endmodule

screen_ws2812b/src/pulse_generator/pulse_generator.v
module pulse_generator #(
    parameter CLK_FREQ_MHZ   = 25,
    parameter T0H_NS         = 400,
    parameter T1H_NS         = 850,
    parameter PULSE_NS       = 1250,
    parameter RESET_PULSE_NS = 100_000
) (
    input  sys_clk,
    input  rst_n,

    input  in_start,
    input  in_bit_in,
    input  in_send_reset,

    output reg out_pulse_out,
    output wire out_high_done,
    output wire out_reset_done,
    output wire out_pulse_done
);

    localparam T0H_CYCLES = (T0H_NS * CLK_FREQ_MHZ)/1000;
    localparam T1H_CYCLES = (T1H_NS * CLK_FREQ_MHZ)/1000;
    localparam PULSE_CYCLES = (PULSE_NS * CLK_FREQ_MHZ)/1000 - 1;
    localparam RESET_CYCLES = (RESET_PULSE_NS * CLK_FREQ_MHZ)/1000;

    localparam IDLE = 3'd0;
    localparam WAIT_HIGH = 3'd1;
    localparam WAIT_PULSE = 3'd2;
    localparam RESET_PHASE = 3'd3;

    reg [2:0] state;
    reg  [15:0] counter;
    reg [15:0] high_cycles;

    assign out_high_done = (counter == high_cycles) & !(state == RESET_PHASE);
    assign out_reset_done = counter == RESET_CYCLES;
    assign out_pulse_done = (counter == PULSE_CYCLES) & !(state == RESET_PHASE);

    always @(negedge sys_clk) begin
        if (!rst_n) begin
            state <= IDLE;
            counter <= 16'd0;
        end else begin
            case (state)
                IDLE: begin
                    counter <= 16'd0;
                    if (in_start) begin
                        high_cycles = in_bit_in ? T1H_CYCLES : T0H_CYCLES;
                        state <= WAIT_HIGH;
                    end else if (in_send_reset) begin
                        state <= RESET_PHASE;
                    end else state <= IDLE;
                end

                WAIT_HIGH: begin
                    if (out_high_done) begin
                        state   <= WAIT_PULSE;
                    end else begin
                        state   <= WAIT_HIGH;
                    end
                    counter <= counter + 16'd1;
                end

                WAIT_PULSE: begin
                    if (out_pulse_done) begin
                        counter <= 16'd0;
                        if (in_start) begin
                            high_cycles = in_bit_in ? T1H_CYCLES : T0H_CYCLES;
                            state <= WAIT_HIGH;
                        end else if (in_send_reset) begin
                            state <= RESET_PHASE;
                        end else state <= IDLE;
                    end else begin
                        counter <= counter + 16'd1;
                        state   <= WAIT_PULSE;
                    end
                end

                RESET_PHASE: begin
                    if (out_reset_done) begin
                        state <= IDLE;
                    end else begin
                        counter <= counter + 16'd1;
                        state   <= RESET_PHASE;
                    end
                end
                default: state <= IDLE;
            endcase
        end
    end

    always @(*) begin
        case (state)
            IDLE: begin
                out_pulse_out <= 1'b0;
            end
            WAIT_HIGH: begin
                out_pulse_out <= 1'b1;
            end
            WAIT_PULSE: begin
                out_pulse_out <= 1'b0;
            end
            RESET_PHASE: begin
                out_pulse_out <= 1'b0;
            end
            default: begin
                out_pulse_out <= 1'b0;
            end
        endcase
    end



`ifdef BENCH
    reg [8*40:1] state_name;
    always @(*) begin
        case (state)
            IDLE:        state_name = "IDLE";
            WAIT_HIGH:  state_name = "WAIT_HIGH";
            WAIT_PULSE:   state_name = "WAIT_PULSE";
            RESET_PHASE: state_name = "RESET_PHASE";
        endcase
    end
`endif

endmodule

screen_ws2812b/src/shift_register/shift_register.v
module shift_register #(
    parameter DATA_WIDTH = 24
)(
    input  sys_clk,
    input  rst_n,
    
    input                    in_load,
    input      [DATA_WIDTH-1:0] in_data,
    input                    in_shift,
    output wire              out_data
);

reg [DATA_WIDTH-1:0] buffer;

assign out_data = buffer[DATA_WIDTH-1];

always @(negedge sys_clk) begin
    if (!rst_n) begin
        buffer <= {DATA_WIDTH{1'b0}};
    end else begin
        if (in_load) begin
            buffer <= in_data;
        end else if (in_shift) begin
            buffer <= {buffer[DATA_WIDTH-2:0],1'b0};
        end
    end
end

endmodule

screen_ws2812b/src/frame_buffer/frame_buffer.v
module frame_buffer #(
    parameter ADDR_WIDTH = 8,
    parameter DATA_WIDTH = 24
)(
    input  sys_clk,
    
    input      [ADDR_WIDTH-1:0] in_write_addr,
    input                       in_write_enable,
    input      [DATA_WIDTH-1:0] in_color_in,
    
    input      [ADDR_WIDTH-1:0] in_read_addr,
    input                       in_read_enable,
    output reg [DATA_WIDTH-1:0] out_color_out
);

reg [DATA_WIDTH-1:0] memory [0:2**ADDR_WIDTH-1];
initial begin
    $readmemh("/home/samuel/Repositories/Digital2_pero_no_estoy_inscrito/screen_ws2812b/src/frame_buffer/test_benches/imagen.hex",memory);
end
always @(negedge sys_clk) begin
    if (in_read_enable) begin
        out_color_out <= memory[in_read_addr];
    end
    if (in_write_enable) begin
        memory[in_write_addr] <= in_color_in;
    end
end

endmodule

screen_ws2812b/src/screen_controller.v
module screen_controller #(
    parameter CLK_FREQ_MHZ = 25,
    parameter QTY_PIXELS = 64
)(
    input  sys_clk,
    input  rst_n,
    
    input      [7:0] in_pixel_addr,
    input      [23:0] in_pixel_color,
    input            in_pixel_we,
    input  in_init_screen,
    output out_data_out
);

wire [7:0] w_fb_read_addr;
wire       w_fb_read_enable;
wire [23:0] w_fb_color_out;

wire       w_shift_load;
wire       w_shift_shift;
wire       w_shift_data_out;

wire       w_pulse_start;
wire       w_pulse_send_reset;
wire       w_pulse_high_done;
wire       w_pulse_reset_done;
wire       w_pulse_done_from_pulse_gen;

frame_buffer #(
    .ADDR_WIDTH($clog2(QTY_PIXELS)),
    .DATA_WIDTH(24)
) u_frame_buffer (
    .sys_clk(sys_clk),
    .in_write_addr(in_pixel_addr),
    .in_write_enable(in_pixel_we),
    .in_color_in(in_pixel_color),
    .in_read_addr(w_fb_read_addr),
    .in_read_enable(w_fb_read_enable),
    .out_color_out(w_fb_color_out)
);

shift_register #(
    .DATA_WIDTH(24)
) u_shift_register (
    .sys_clk(sys_clk),
    .rst_n(rst_n),
    .in_load(w_shift_load),
    .in_data(w_fb_color_out),
    .in_shift(w_shift_shift),
    .out_data(w_shift_data_out)
);

pulse_generator #(
    .CLK_FREQ_MHZ(CLK_FREQ_MHZ)
) u_pulse_generator (
    .sys_clk(sys_clk),
    .rst_n(rst_n),
    .in_start(w_pulse_start),
    .in_bit_in(w_shift_data_out),
    .in_send_reset(w_pulse_send_reset),
    .out_pulse_out(out_data_out),
    .out_high_done(w_pulse_high_done),
    .out_reset_done(w_pulse_reset_done),
    .out_pulse_done(w_pulse_done_from_pulse_gen)
);

screen_fsm #(
    .LED_COUNT(QTY_PIXELS),
    .BITS_COUNT(24)
) u_fsm (
    .sys_clk(sys_clk),
    .rst_n(rst_n),
    .in_init(in_init_screen),
    .out_fb_read_addr(w_fb_read_addr),
    .out_fb_read_enable(w_fb_read_enable),
    .out_shift_load(w_shift_load),
    .out_shift_shift(w_shift_shift),
    .out_pulse_start(w_pulse_start),
    .out_pulse_send_reset(w_pulse_send_reset),
    .in_pulse_high_done(w_pulse_high_done),
    .in_pulse_reset_done(w_pulse_reset_done),
    .in_pulse_done(w_pulse_done_from_pulse_gen)
);

endmodule

screen_ws2812b/src/test_benches/screen_controller_tb.v
`timescale 1ns / 1ps

module screen_controller_tb;

localparam RST_VALUE_PC = 8'd254;

reg sys_clk;
reg rst_n;

reg [7:0] pixel_addr;
reg [23:0] pixel_color;
reg       pixel_we;
reg run_screen;
wire data_out;

screen_controller #(
    .CLK_FREQ_MHZ(25),
    .QTY_PIXELS(64)
) uut (
    .sys_clk(sys_clk),
    .rst_n(rst_n),
    .in_pixel_addr(pixel_addr),
    .in_pixel_color(pixel_color),
    .in_pixel_we(pixel_we),
    .in_init_screen(run_screen),
    .out_data_out(data_out)
);

always #20 sys_clk = ~sys_clk;

integer i;

initial begin
    $dumpfile("screen_controller_tb.vcd");
    $dumpvars(0, screen_controller_tb);
    $timeformat(-9, 0, "ns", 5);
    
    sys_clk = 0;
    rst_n = 1;
    pixel_addr = 0;
    pixel_color = 0;
    pixel_we = 0;
    run_screen = 0;
    #50 rst_n = 0;
    #40 rst_n = 1;
    // $display("Writing pixel data...");
    
    // for (i = RST_VALUE_PC; i < 3+RST_VALUE_PC; i = i + 1) begin
    //     @(posedge sys_clk);
    //     pixel_addr = i;
    //     pixel_color = 24'h0000AA >> i-RST_VALUE_PC;
    //     pixel_we = 1;
    //     @(posedge sys_clk);
    //     pixel_we = 0;
    //     #100;
    // end
    
    $display("Starting frame transmission...");
    @(negedge sys_clk);
    run_screen = 1;
    @(negedge sys_clk);
    run_screen = 0;
    $display("Watching first few bits...");
    
    #1_950_000;
    
    $display("Controller test completed - check waveform");
    $finish;
end

endmodule

screen_ws2812b/src/simulation/simple/screen_controller/screen_controller_tb.vcd
$date
	Thu May  7 16:36:30 2026
$end
$version
	Icarus Verilog
$end
$timescale
	1ps
$end
$scope module screen_controller_tb $end
$var wire 1 ! data_out $end
$var parameter 8 " RST_VALUE_PC $end
$var reg 8 # pixel_addr [7:0] $end
$var reg 24 $ pixel_color [23:0] $end
$var reg 1 % pixel_we $end
$var reg 1 & rst_n $end
$var reg 1 ' run_screen $end
$var reg 1 ( sys_clk $end
$scope module uut $end
$var wire 1 ' in_init_screen $end
$var wire 8 ) in_pixel_addr [7:0] $end
$var wire 24 * in_pixel_color [23:0] $end
$var wire 1 % in_pixel_we $end
$var wire 1 & rst_n $end
$var wire 1 ( sys_clk $end
$var wire 1 + w_shift_shift $end
$var wire 1 , w_shift_load $end
$var wire 1 - w_shift_data_out $end
$var wire 1 . w_pulse_start $end
$var wire 1 / w_pulse_send_reset $end
$var wire 1 0 w_pulse_reset_done $end
$var wire 1 1 w_pulse_high_done $end
$var wire 1 2 w_pulse_done_from_pulse_gen $end
$var wire 1 3 w_fb_read_enable $end
$var wire 8 4 w_fb_read_addr [7:0] $end
$var wire 24 5 w_fb_color_out [23:0] $end
$var wire 1 ! out_data_out $end
$var parameter 32 6 CLK_FREQ_MHZ $end
$var parameter 32 7 QTY_PIXELS $end
$scope module u_frame_buffer $end
$var wire 24 8 in_color_in [23:0] $end
$var wire 6 9 in_read_addr [5:0] $end
$var wire 6 : in_write_addr [5:0] $end
$var wire 1 % in_write_enable $end
$var wire 1 ( sys_clk $end
$var wire 1 3 in_read_enable $end
$var parameter 32 ; ADDR_WIDTH $end
$var parameter 32 < DATA_WIDTH $end
$var reg 24 = out_color_out [23:0] $end
$upscope $end
$scope module u_fsm $end
$var wire 1 ' in_init $end
$var wire 1 & rst_n $end
$var wire 1 ( sys_clk $end
$var wire 8 > out_fb_read_addr [7:0] $end
$var wire 1 0 in_pulse_reset_done $end
$var wire 1 1 in_pulse_high_done $end
$var wire 1 2 in_pulse_done $end
$var parameter 32 ? BITS_COUNT $end
$var parameter 5 @ CHECK_BITS $end
$var parameter 32 A LED_COUNT $end
$var parameter 5 B LOAD_SHIFT $end
$var parameter 5 C NEXT_PIXEL $end
$var parameter 5 D READ_PIXEL $end
$var parameter 8 E RST_VALUE_PC $end
$var parameter 5 F RUN_SCREEN $end
$var parameter 5 G SEND_RESET $end
$var parameter 5 H SHIFT_NEXT $end
$var parameter 5 I START $end
$var parameter 5 J WAIT_HIGH $end
$var parameter 5 K WAIT_PULSE $end
$var parameter 5 L WAIT_RESET $end
$var reg 5 M bit_counter [4:0] $end
$var reg 1 3 out_fb_read_enable $end
$var reg 1 / out_pulse_send_reset $end
$var reg 1 . out_pulse_start $end
$var reg 1 , out_shift_load $end
$var reg 1 + out_shift_shift $end
$var reg 8 N pixel_counter [7:0] $end
$var reg 5 O state [4:0] $end
$var reg 320 P state_name [320:1] $end
$upscope $end
$scope module u_pulse_generator $end
$var wire 1 / in_send_reset $end
$var wire 1 . in_start $end
$var wire 1 1 out_high_done $end
$var wire 1 2 out_pulse_done $end
$var wire 1 & rst_n $end
$var wire 1 ( sys_clk $end
$var wire 1 0 out_reset_done $end
$var wire 1 - in_bit_in $end
$var parameter 32 Q CLK_FREQ_MHZ $end
$var parameter 3 R IDLE $end
$var parameter 65 S PULSE_CYCLES $end
$var parameter 32 T PULSE_NS $end
$var parameter 64 U RESET_CYCLES $end
$var parameter 3 V RESET_PHASE $end
$var parameter 32 W RESET_PULSE_NS $end
$var parameter 64 X T0H_CYCLES $end
$var parameter 32 Y T0H_NS $end
$var parameter 64 Z T1H_CYCLES $end
$var parameter 32 [ T1H_NS $end
$var parameter 3 \ WAIT_HIGH $end
$var parameter 3 ] WAIT_PULSE $end
$var reg 16 ^ counter [15:0] $end
$var reg 16 _ high_cycles [15:0] $end
$var reg 1 ! out_pulse_out $end
$var reg 3 ` state [2:0] $end
$var reg 320 a state_name [320:1] $end
$upscope $end
$scope module u_shift_register $end
$var wire 24 b in_data [23:0] $end
$var wire 1 , in_load $end
$var wire 1 + in_shift $end
$var wire 1 & rst_n $end
$var wire 1 ( sys_clk $end
$var wire 1 - out_data $end
$var parameter 32 c DATA_WIDTH $end
$var reg 24 d buffer [23:0] $end
$upscope $end
$upscope $end
$upscope $end
$enddefinitions $end
$comment Show the parameter values. $end
$dumpall
b11000 c
b10 ]
b1 \
b1101010010 [
b10101 Z
b110010000 Y
b1010 X
b11000011010100000 W
b11 V
b100111000100 U
b10011100010 T
b11110 S
b0 R
b11001 Q
b1001 L
b1010 K
b100 J
b0 I
b101 H
b1000 G
b11 F
b0 E
b1 D
b111 C
b10 B
b1000000 A
b110 @
b11000 ?
b11000 <
b110 ;
b1000000 7
b11001 6
b11111110 "
$end
#0
$dumpvars
bx d
bx b
b1001001010001000100110001000101 a
b0 `
bx _
bx ^
bx P
bx O
bx N
bx M
bx >
bx =
b0 :
bx 9
b0 8
bx 5
bx 4
x3
x2
x1
x0
x/
x.
x-
x,
x+
b0 *
b0 )
0(
0'
1&
0%
b0 $
b0 #
0!
$end
#20000
b101001101010100010000010101001001010100 P
0/
0.
0+
0,
03
b0 O
1(
#40000
02
00
b0 ^
0(
#50000
0&
#60000
b0 9
b0 4
b0 >
b0 N
b0 M
1(
#80000
0-
b0 d
0(
#90000
1&
#100000
1(
#120000
1'
0(
#140000
13
b1010010010001010100000101000100010111110101000001001001010110000100010101001100 P
b1 O
1(
#160000
b111111111111111111111111 5
b111111111111111111111111 =
b111111111111111111111111 b
0'
0(
#180000
b1001100010011110100000101000100010111110101001101001000010010010100011001010100 P
1,
03
b10 O
1(
#200000
1-
b111111111111111111111111 d
0(
#220000
1.
0,
b1010010010101010100111001011111010100110100001101010010010001010100010101001110 P
b11 O
1(
#240000
1!
b10101110100000101001001010101000101111101001000010010010100011101001000 a
b1 `
01
b10101 _
0(
#260000
b10101110100000101001001010101000101111101001000010010010100011101001000 P
b100 O
1(
#280000
b1 ^
0(
#300000
1(
#320000
b10 ^
0(
#340000
1(
#360000
b11 ^
0(
#380000
1(
#400000
b100 ^
0(
#420000
1(
#440000
b101 ^
0(
#460000
1(
#480000
b110 ^
0(
#500000
1(
#520000
b111 ^
0(
#540000
1(
#560000
b1000 ^
0(
#580000
1(
#600000
b1001 ^
0(
#620000
1(
#640000
b1010 ^
0(
#660000
1(
#680000
b1011 ^
0(
#700000
1(
#720000
b1100 ^
0(
#740000
1(
#760000
b1101 ^
0(
#780000
1(
#800000
b1110 ^
0(
#820000
1(
#840000
b1111 ^
0(
#860000
1(
#880000
b10000 ^
0(
#900000
1(
#920000
b10001 ^
0(
#940000
1(
#960000
b10010 ^
0(
#980000
1(
#1000000
b10011 ^
0(
#1020000
1(
#1040000
b10100 ^
0(
#1060000
1(
#1080000
11
b10101 ^
0(
#1100000
1+
b1010011010010000100100101000110010101000101111101001110010001010101100001010100 P
b101 O
1(
#1120000
0!
01
b1010111010000010100100101010100010111110101000001010101010011000101001101000101 a
b111111111111111111111110 d
b10110 ^
b10 `
0(
#1140000
b1000011010010000100010101000011010010110101111101000010010010010101010001010011 P
0+
b1 M
b110 O
1(
#1160000
b10111 ^
0(
#1180000
b10101110100000101001001010101000101111101001000010010010100011101001000 P
b100 O
1(
#1200000
b11000 ^
0(
#1220000
1(
#1240000
b11001 ^
0(
#1260000
1(
#1280000
b11010 ^
0(
#1300000
1(
#1320000
b11011 ^
0(
#1340000
1(
#1360000
b11100 ^
0(
#1380000
1(
#1400000
b11101 ^
0(
#1420000
1(
#1440000
12
b11110 ^
0(
#1460000
1(
#1480000
1!
02
b10101110100000101001001010101000101111101001000010010010100011101001000 a
b1 `
b0 ^
0(
#1500000
1(
#1520000
b1 ^
0(
#1540000
1(
#1560000
b10 ^
0(
#1580000
1(
#1600000
b11 ^
0(
#1620000
1(
#1640000
b100 ^
0(
#1660000
1(
#1680000
b101 ^
0(
#1700000
1(
#1720000
b110 ^
0(
#1740000
1(
#1760000
b111 ^
0(
#1780000
1(
#1800000
b1000 ^
0(
#1820000
1(
#1840000
b1001 ^
0(
#1860000
1(
#1880000
b1010 ^
0(
#1900000
1(
#1920000
b1011 ^
0(
#1940000
1(
#1960000
b1100 ^
0(
#1980000
1(
#2000000
b1101 ^
0(
#2020000
1(
#2040000
b1110 ^
0(
#2060000
1(
#2080000
b1111 ^
0(
#2100000
1(
#2120000
b10000 ^
0(
#2140000
1(
#2160000
b10001 ^
0(
#2180000
1(
#2200000
b10010 ^
0(
#2220000
1(
#2240000
b10011 ^
0(
#2260000
1(
#2280000
b10100 ^
0(
#2300000
1(
#2320000
11
b10101 ^
0(
#2340000
b1010011010010000100100101000110010101000101111101001110010001010101100001010100 P
1+
b101 O
1(
#2360000
0!
01
b1010111010000010100100101010100010111110101000001010101010011000101001101000101 a
b10110 ^
b10 `
b111111111111111111111100 d
0(
#2380000
0+
b1000011010010000100010101000011010010110101111101000010010010010101010001010011 P
b10 M
b110 O
1(
#2400000
b10111 ^
0(
#2420000
b10101110100000101001001010101000101111101001000010010010100011101001000 P
b100 O
1(
#2440000
b11000 ^
0(
#2460000
1(
#2480000
b11001 ^
0(
#2500000
1(
#2520000
b11010 ^
0(
#2540000
1(
#2560000
b11011 ^
0(
#2580000
1(
#2600000
b11100 ^
0(
#2620000
1(
#2640000
b11101 ^
0(
#2660000
1(
#2680000
12
b11110 ^
0(
#2700000
1(
#2720000
1!
02
b10101110100000101001001010101000101111101001000010010010100011101001000 a
b1 `
b0 ^
0(
#2740000
1(
#2760000
b1 ^
0(
#2780000
1(
#2800000
b10 ^
0(
#2820000
1(
#2840000
b11 ^
0(
#2860000
1(
#2880000
b100 ^
0(
#2900000
1(
#2920000
b101 ^
0(
#2940000
1(
#2960000
b110 ^
0(
#2980000
1(
#3000000
b111 ^
0(
#3020000
1(
#3040000
b1000 ^
0(
#3060000
1(
#3080000
b1001 ^
0(
#3100000
1(
#3120000
b1010 ^
0(
#3140000
1(
#3160000
b1011 ^
0(
#3180000
1(
#3200000
b1100 ^
0(
#3220000
1(
#3240000
b1101 ^
0(
#3260000
1(
#3280000
b1110 ^
0(
#3300000
1(
#3320000
b1111 ^
0(
#3340000
1(
#3360000
b10000 ^
0(
#3380000
1(
#3400000
b10001 ^
0(
#3420000
1(
#3440000
b10010 ^
0(
#3460000
1(
#3480000
b10011 ^
0(
#3500000
1(
#3520000
b10100 ^
0(
#3540000
1(
#3560000
11
b10101 ^
0(
#3580000
1+
b1010011010010000100100101000110010101000101111101001110010001010101100001010100 P
b101 O
1(
#3600000
0!
01
b1010111010000010100100101010100010111110101000001010101010011000101001101000101 a
b111111111111111111111000 d
b10110 ^
b10 `
0(
#3620000
b1000011010010000100010101000011010010110101111101000010010010010101010001010011 P
0+
b11 M
b110 O
1(
#3640000
b10111 ^
0(
#3660000
b10101110100000101001001010101000101111101001000010010010100011101001000 P
b100 O
1(
#3680000
b11000 ^
0(
#3700000
1(
#3720000
b11001 ^
0(
#3740000
1(
#3760000
b11010 ^
0(
#3780000
1(
#3800000
b11011 ^
0(
#3820000
1(
#3840000
b11100 ^
0(
#3860000
1(
#3880000
b11101 ^
0(
#3900000
1(
#3920000
12
b11110 ^
0(
#3940000
1(
#3960000
1!
02
b10101110100000101001001010101000101111101001000010010010100011101001000 a
b1 `
b0 ^
0(
#3980000
1(
#4000000
b1 ^
0(
#4020000
1(
#4040000
b10 ^
0(
#4060000
1(
#4080000
b11 ^
0(
#4100000
1(
#4120000
b100 ^
0(
#4140000
1(
#4160000
b101 ^
0(
#4180000
1(
#4200000
b110 ^
0(
#4220000
1(
#4240000
b111 ^
0(
#4260000
1(
#4280000
b1000 ^
0(
#4300000
1(
#4320000
b1001 ^
0(
#4340000
1(
#4360000
b1010 ^
0(
#4380000
1(
#4400000
b1011 ^
0(
#4420000
1(
#4440000
b1100 ^
0(
#4460000
1(
#4480000
b1101 ^
0(
#4500000
1(
#4520000
b1110 ^
0(
#4540000
1(
#4560000
b1111 ^
0(
#4580000
1(
#4600000
b10000 ^
0(
#4620000
1(
#4640000
b10001 ^
0(
#4660000
1(
#4680000
b10010 ^
0(
#4700000
1(
#4720000
b10011 ^
0(
#4740000
1(
#4760000
b10100 ^
0(
#4780000
1(
#4800000
11
b10101 ^
0(
#4820000
b1010011010010000100100101000110010101000101111101001110010001010101100001010100 P
1+
b101 O
1(
#4840000
0!
01
b1010111010000010100100101010100010111110101000001010101010011000101001101000101 a
b10110 ^
b10 `
b111111111111111111110000 d
0(
#4860000
0+
b1000011010010000100010101000011010010110101111101000010010010010101010001010011 P
b100 M
b110 O
1(
#4880000
b10111 ^
0(
#4900000
b10101110100000101001001010101000101111101001000010010010100011101001000 P
b100 O
1(
#4920000
b11000 ^
0(
#4940000
1(
#4960000
b11001 ^
0(
#4980000
1(
#5000000
b11010 ^
0(
#5020000
1(
#5040000
b11011 ^
0(
#5060000
1(
#5080000
b11100 ^
0(
#5100000
1(
#5120000
b11101 ^
0(
#5140000
1(
#5160000
12
b11110 ^
0(
#5180000
1(
#5200000
1!
02
b10101110100000101001001010101000101111101001000010010010100011101001000 a
b1 `
b0 ^
0(
#5220000
1(
#5240000
b1 ^
0(
#5260000
1(
#5280000
b10 ^
0(
#5300000
1(
#5320000
b11 ^
0(
#5340000
1(
#5360000
b100 ^
0(
#5380000
1(
#5400000
b101 ^
0(
#5420000
1(
#5440000
b110 ^
0(
#5460000
1(
#5480000
b111 ^
0(
#5500000
1(
#5520000
b1000 ^
0(
#5540000
1(
#5560000
b1001 ^
0(
#5580000
1(
#5600000
b1010 ^
0(
#5620000
1(
#5640000
b1011 ^
0(
#5660000
1(
#5680000
b1100 ^
0(
#5700000
1(
#5720000
b1101 ^
0(
#5740000
1(
#5760000
b1110 ^
0(
#5780000
1(
#5800000
b1111 ^
0(
#5820000
1(
#5840000
b10000 ^
0(
#5860000
1(
#5880000
b10001 ^
0(
#5900000
1(
#5920000
b10010 ^
0(
#5940000
1(
#5960000
b10011 ^
0(
#5980000
1(
#6000000
b10100 ^
0(
#6020000
1(
#6040000
11
b10101 ^
0(
#6060000
1+
b1010011010010000100100101000110010101000101111101001110010001010101100001010100 P
b101 O
1(
#6080000
0!
01
b1010111010000010100100101010100010111110101000001010101010011000101001101000101 a
b111111111111111111100000 d
b10110 ^
b10 `
0(
#6100000
b1000011010010000100010101000011010010110101111101000010010010010101010001010011 P
0+
b101 M
b110 O
1(
#6120000
b10111 ^
0(
#6140000
b10101110100000101001001010101000101111101001000010010010100011101001000 P
b100 O
1(
#6160000
b11000 ^
0(
#6180000
1(
#6200000
b11001 ^
0(
#6220000
1(
#6240000
b11010 ^
0(
#6260000
1(
#6280000
b11011 ^
0(
#6300000
1(
#6320000
b11100 ^
0(
#6340000
1(
#6360000
b11101 ^
0(
#6380000
1(
#6400000
12
b11110 ^
0(
#6420000
1(
#6440000
1!
02
b10101110100000101001001010101000101111101001000010010010100011101001000 a
b1 `
b0 ^
0(
#6460000
1(
#6480000
b1 ^
0(
#6500000
1(
#6520000
b10 ^
0(
#6540000
1(
#6560000
b11 ^
0(
#6580000
1(
#6600000
b100 ^
0(
#6620000
1(
#6640000
b101 ^
0(
#6660000
1(
#6680000
b110 ^
0(
#6700000
1(
#6720000
b111 ^
0(
#6740000
1(
#6760000
b1000 ^
0(
#6780000
1(
#6800000
b1001 ^
0(
#6820000
1(
#6840000
b1010 ^
0(
#6860000
1(
#6880000
b1011 ^
0(
#6900000
1(
#6920000
b1100 ^
0(
#6940000
1(
#6960000
b1101 ^
0(
#6980000
1(
#7000000
b1110 ^
0(
#7020000
1(
#7040000
b1111 ^
0(
#7060000
1(
#7080000
b10000 ^
0(
#7100000
1(
#7120000
b10001 ^
0(
#7140000
1(
#7160000
b10010 ^
0(
#7180000
1(
#7200000
b10011 ^
0(
#7220000
1(
#7240000
b10100 ^
0(
